triton_kernels/__init__.py
triton_kernels/add_vectors.py
triton_kernels/add_vectors2.py
triton_kernels/rotary_embedding.py
triton_kernels/utils/__init__.py
triton_kernels/utils/generate_kernel_binaries.py
triton_kernels/utils/kernel_mapper.py
triton_kernels-0.1.0.dist-info/METADATA
triton_kernels-0.1.0.dist-info/WHEEL
triton_kernels-0.1.0.dist-info/entry_points.txt
triton_kernels-0.1.0.dist-info/top_level.txt
triton_kernels-0.1.0.dist-info/RECORD
